Metadata-Version: 2.1
Name: automate-office
Version: 0.3.1
Summary: Offic自动化工具-自用，在原有包的基础上二次开发, PPT部分暂时告一段落, Word暂时用处不大, Excel做了一些函数和例子
Home-page: 
Author: Sun Meng
Author-email: clivesun@163.com
Classifier: Development Status :: 3 - Alpha
Classifier: Intended Audience :: Developers
Classifier: Topic :: Software Development :: Build Tools
Classifier: License :: OSI Approved :: MIT License
Classifier: Programming Language :: Python :: 3
Classifier: Programming Language :: Python :: 3.10
License-File: LICENSE
Requires-Dist: python-docx ==1.1.0
Requires-Dist: python-pptx ==0.6.23
Requires-Dist: openpyxl ==3.1.2
